AUTHORS.rst
CONTRIBUTING.rst
HISTORY.rst
LICENSE
MANIFEST.in
README.rst
setup.py
gitcoach/__init__.py
gitcoach/coach.py
gitcoach/commands.py
gitcoach/gitcoach.py
gitcoach/learn.py
gitcoach.egg-info/PKG-INFO
gitcoach.egg-info/SOURCES.txt
gitcoach.egg-info/dependency_links.txt
gitcoach.egg-info/entry_points.txt
gitcoach.egg-info/not-zip-safe
gitcoach.egg-info/requires.txt
gitcoach.egg-info/top_level.txt