Metadata-Version: 1.1
Name: gitcoach
Version: 0.2.2
Summary: Help you find out what files you should be changing.
Home-page: https://github.com/mhoye/gitcoach
Author: Mike Hoye
Author-email: mhoye@mozilla.com
License: BSD
Keywords: gitcoach
Platform: UNKNOWN
Classifier: Development Status :: 2 - Pre-Alpha
Classifier: Intended Audience :: Developers
Classifier: License :: OSI Approved :: BSD License
Classifier: Natural Language :: English
Classifier: Programming Language :: Python :: 2
Classifier: Programming Language :: Python :: 2.6
Classifier: Programming Language :: Python :: 2.7
Classifier: Programming Language :: Python :: 3
Classifier: Programming Language :: Python :: 3.3
